dailyReportHandler/DailyReportHandler.py
dailyReportHandler/Template.py
dailyReportHandler/Utils.py
dailyReportHandler/__init__.py
dailyReportHandler/cmd.py
dailyReportHandler/daily.py
dailyReportHandler/workFlowHandler.py
dailyReportHandler-1.0.2.dist-info/METADATA
dailyReportHandler-1.0.2.dist-info/WHEEL
dailyReportHandler-1.0.2.dist-info/entry_points.txt
dailyReportHandler-1.0.2.dist-info/top_level.txt
dailyReportHandler-1.0.2.dist-info/RECORD
