Metadata-Version: 2.1
Name: dailyReportHandler
Version: 1.0.2
Summary: A file manager to generate daily report
Home-page: https://github.com/dancehole/dailyReportHandler
Author: Dancehole
Author-email: 1391755954@qq.com
License: UNKNOWN
Platform: UNKNOWN
Classifier: Programming Language :: Python :: 3
Classifier: License :: OSI Approved :: MIT License
Classifier: Operating System :: OS Independent
Requires-Dist: requests
